{
  "ItemType": 1,
  "Id": 9027,
  "Name": "Screener",
  "Description": "Made mostly from repurposed Chaser parts but incorporating automated systems and weapons the Korath Exiles recently re-acquired, the Screener is a new fighter that sacrifices movement ability to to field enough small missile launchers to overcome most defensive systems.",
  "DisplayCategory": 5,
  "Availability": 2,
  "ComponentStatsId": 9027,
  "Faction": 213,
  "Level": 400,
  "Icon": "screener icon.png",
  "Layout": "111111111",
  "CellType": "1",
  "DroneBayId": 9027,
  "DroneId": 9027,
  "PossibleModifications": [
    17,
    18,
    19,
    20,
    2
  ]
}